AUTHORS.rst
CONTRIBUTING.rst
HISTORY.rst
LICENSE
MANIFEST.in
README.rst
setup.cfg
setup.py
docs/Makefile
docs/authors.rst
docs/conf.py
docs/contributing.rst
docs/history.rst
docs/index.rst
docs/installation.rst
docs/make.bat
docs/modules.rst
docs/pywim.rst
docs/readme.rst
docs/usage.rst
pywim/__init__.py
pywim.egg-info/PKG-INFO
pywim.egg-info/SOURCES.txt
pywim.egg-info/dependency_links.txt
pywim.egg-info/not-zip-safe
pywim.egg-info/requires.txt
pywim.egg-info/top_level.txt
tests/__init__.py
tests/test_pywim.py