Metadata-Version: 1.1
Name: pywim
Version: 0.1.0
Summary: Open algorithms to use in WIM research
Home-page: https://github.com/OpenWIM/pywim
Author: Ivan Ogasawara
Author-email: ivan.ogasawara@gmail.com
License: MIT license
Keywords: pywim
Platform: UNKNOWN
Classifier: Development Status :: 2 - Pre-Alpha
Classifier: Intended Audience :: Developers
Classifier: License :: OSI Approved :: MIT License
Classifier: Natural Language :: English
Classifier: Programming Language :: Python :: 3
Classifier: Programming Language :: Python :: 3.4
Classifier: Programming Language :: Python :: 3.5
